slgps/SL_GPS.py
slgps/__init__.py
slgps/display_sim_data.py
slgps/drgep_red_mech.py
slgps/example.py
slgps/h5topb.py
slgps/main.py
slgps/main_series.py
slgps/make_data.py
slgps/make_data_parallel.py
slgps/mech_train.py
slgps/mech_train_new.py
slgps/new_data_utils.py
slgps/parallel_old.py
slgps/reduce_drgep_short.py
slgps/setup.py
slgps/sup_plot.py
slgps/sup_test.py
slgps/testPython.py
slgps/train_data_2D.py
slgps/train_data_2D_parallel.py
slgps/utils.py
slgps/GPS/src/__init__.py
slgps/GPS/src/ck/__init__.py
slgps/GPS/src/ck/def_build_mech_dict.py
slgps/GPS/src/ck/def_build_raw_npz.py
slgps/GPS/src/ck/def_cheminp.py
slgps/GPS/src/ck/upper_cheminp.py
slgps/GPS/src/core/__init__.py
slgps/GPS/src/core/def_GPS.py
slgps/GPS/src/core/def_GPSA.py
slgps/GPS/src/core/def_PFA.py
slgps/GPS/src/core/def_build_graph.py
slgps/GPS/src/core/def_tools.py
slgps/GPS/src/core/def_yen.py
slgps/GPS/src/ct/__init__.py
slgps/GPS/src/ct/ck2cti_GPS.py
slgps/GPS/src/ct/ck2cti_GPS_kcal.py
slgps/GPS/src/ct/def_ct_tools.py
slgps/GPS/src/ct/dialog_view_mech.py
slgps/GPS/src/ct/psr.py
slgps/GPS/src/ct/senkin.py
slgps/GPS/src/gui/__init__.py
slgps/GPS/src/gui/def_dialog.py
slgps/GPS/src/gui/def_run.py
slgps/GPS/src/gui/dialog_GPS.py
slgps/GPS/src/gui/dialog_GPS_es.py
slgps/GPS/src/gui/dialog_about.py
slgps/GPS/src/gui/dialog_comb_sk.py
slgps/GPS/src/gui/dialog_database.py
slgps/GPS/src/gui/dialog_database_mixture.py
slgps/GPS/src/gui/dialog_mech.py
slgps/GPS/src/gui/dialog_view_mech.py
slgps/GPS/src/gui/find_tau_ign.py
slgps/GPS/src/gui/window_main.py
slgps/GPS/src/post/__init__.py
slgps/GPS/src/post/def_painter.py
slgps/GPS/src/post/def_plt_tools.py
slgps/GPS/src/post/dialog_post.py
slgps/GPS/src/post/dialog_rename.py
slgps/GPS/src/post/dialog_subplot.py
slgps/GPS/src/tools/__init__.py
slgps/GPS/src/tools/add_root_path.py
slgps/GPS/src/tools/ck_data_reader.py
slgps/GPS/src/tools/combine_de_mech.py
slgps/GPS/src/tools/csv_plot.py
slgps/GPS/src/tools/def_DNS.py
slgps/GPS/src/tools/upper_case.py
slgps-0.0.1.dist-info/LICENSE
slgps-0.0.1.dist-info/METADATA
slgps-0.0.1.dist-info/WHEEL
slgps-0.0.1.dist-info/top_level.txt
slgps-0.0.1.dist-info/RECORD
