Metadata-Version: 2.2
Name: slgps
Version: 0.0.1
Summary: NN assisted chemistry reduction of mechanism based on Global Pathway Selection algorithm
Author-email: Rohit Mishra <rohitmishranitrr@gmail.com>
Project-URL: Homepage, https://github.com/ctftamu/SL-GPS
Project-URL: Issues, https://github.com/ctftamu/SL-GPS/issues
Classifier: Programming Language :: Python :: 3
Classifier: License :: OSI Approved :: MIT License
Classifier: Operating System :: OS Independent
Requires-Python: >=3.8
License-File: LICENSE
